treeman/__init__.py
treeman/cli.py
treeman/core.py
treeman-0.1.2.dist-info/licenses/LICENSE
treeman-0.1.2.dist-info/METADATA
treeman-0.1.2.dist-info/WHEEL
treeman-0.1.2.dist-info/entry_points.txt
treeman-0.1.2.dist-info/top_level.txt
treeman-0.1.2.dist-info/RECORD
