Metadata-Version: 2.4
Name: treeman
Version: 0.1.2
Summary: A modern, gitignore-aware directory tree visualizer
Author: Soham Joshi
License: MIT License
Requires-Python: >=3.8
License-File: LICENSE
Requires-Dist: pathspec>=0.11.1
Dynamic: license-file
